conn_diag/__init__.py
conn_diag/__main__.py
conn_diag/cli.py
conn_diag/conn_diag/__init__.py
conn_diag/conn_diag/connection_manager.py
conn_diag/conn_diag/connectivity.py
conn_diag/conn_diag/constants.py
conn_diag/conn_diag/core.py
conn_diag/conn_diag/exceptions.py
conn_diag/conn_diag/result.py
conn_diag/conn_diag/utilities.py
conn_diag/conn_diag/scripts/bash_script.sh
conn_diag/conn_parser/__init__.py
conn_diag/conn_parser/constants.py
conn_diag/conn_parser/core.py
conn_diag/conn_parser/dump.py
conn_diag/conn_parser/dumps.py
conn_diag/conn_parser/exceptions.py
conn_diag/conn_parser/models.py
conn_diag/conn_parser/parse.py
conn_diag/conn_parser/utilities.py
conn_diag-0.0.2.dist-info/METADATA
conn_diag-0.0.2.dist-info/WHEEL
conn_diag-0.0.2.dist-info/entry_points.txt
conn_diag-0.0.2.dist-info/top_level.txt
conn_diag-0.0.2.dist-info/RECORD
